LICENSE.txt
MANIFEST.in
README.md
setup.cfg
setup.py
charc_math/__init__.py
charc_math/gcd.py
charc_math/is_ap.py
charc_math/is_gp.py
charc_math/is_palindrome.py
charc_math/is_prime.py
charc_math/is_seq.py
charc_math/lcm.py
charc_math/primes.py
charc_math/start.py
charc_math/to_base.py
charc_math/to_base10.py
charc_math.egg-info/PKG-INFO
charc_math.egg-info/SOURCES.txt
charc_math.egg-info/dependency_links.txt
charc_math.egg-info/not-zip-safe
charc_math.egg-info/requires.txt
charc_math.egg-info/top_level.txt