Metadata-Version: 1.1
Name: charc-math
Version: 1.1
Summary: Private collection of math functions
Home-page: https://github.com/Charc248/charc_math
Author: Mayur Dave
Author-email: mdave3927@gmail.com
License: MIT
Keywords: math,charc,simple
Platform: UNKNOWN
Classifier: Development Status :: 2 - Pre-Alpha
Classifier: License :: OSI Approved :: MIT License
Classifier: Programming Language :: Python :: 2.7
Classifier: Intended Audience :: Education
